{"code": "07-131", "offered_in_campuses": [1, 2], "offerings": [{"semesters": [{"semester": 2, "year": 2022}], "sub_semesters": [], "campus_id": 2}], "max_units": 2.0, "is_topic": false, "is_repeatable": false, "admin_context": {"counts_for": [], "suggested_by_advisor": null}, "custom_fields": {"key_topics": null, "prerequisite_knowledge": null, "assessment_structure": null, "goals": null, "relevance": null, "learning_resources": null, "extra_time_commitment": null}, "equiv": [], "student_sets": [{"id": 896, "name": "undergraduate"}], "min_units": 2.0, "offering_tags": [{"sem": 1, "type": "INFO", "name": "specific_sem"}], "units": 2.0, "website": null, "long_desc": "SECTION A IS OPEN TO SCS FIRST YEAR STUDENTS ONLY. NonSCS firstyear students should register for section B. Throughout your education as a Computer Scientist at Carnegie Mellon, you will take courses on programming, theoretical ideas, logic, systems, etc. As you progress, you will be expected to pick up the socalled tools of the trade. This course is intended to help you learn what you need to know in a friendly, lowstress, highsupport way. We will discuss UNIX, LaTeX, debugging and many other essential tools. Laptop required. Only undergraduate students will be able to enroll in this course.", "short_name": "GREAT PRAC IDEAS CS", "co_reqs": [{"units": 12.0, "code": "15-112", "id": 5637, "name": "Fundamentals of Programming and Computer Science"}], "instructors": [{"username": "efeoflus", "first_name": "Eduardo", "last_name": "Feo Flushing", "tags": [], "hours_per_week": 0, "id": 4598, "semesters_taught": [{"semester": 2, "year": 2022}], "photo_url": null}, {"username": "greis", "first_name": "Giselle", "last_name": "Reis", "tags": [], "hours_per_week": 0, "id": 636, "semesters_taught": [{"semester": 2, "year": 2022}], "photo_url": null}], "anti_reqs": [], "prereqs": {"text": "", "raw_pre_req": "", "req_obj": null}, "is_req_repeatable": false, "topic": null, "name": "Great Practical Ideas for Computer Scientists", "base_name": "Great Practical Ideas for Computer Scientists", "skills": [], "success": true, "attributes": []}