{"code": "62-210", "offered_in_campuses": [2], "offerings": [{"semesters": [{"semester": 1, "year": 2020}], "sub_semesters": [], "campus_id": 2}], "max_units": 3.0, "is_topic": false, "is_repeatable": false, "admin_context": {"counts_for": [], "suggested_by_advisor": null}, "custom_fields": {"key_topics": null, "prerequisite_knowledge": null, "assessment_structure": null, "goals": null, "relevance": null, "learning_resources": null, "extra_time_commitment": null}, "equiv": [], "student_sets": [{"id": 896, "name": "undergraduate"}], "min_units": 3.0, "offering_tags": [{"sem": 1, "type": "INFO", "name": "specific_sem"}, {"sem": 2, "type": "INFO", "name": "specific_sem"}], "units": 3.0, "website": null, "long_desc": "The title of this microcourse takes it name from the dominant geometric figures found in islamic style patterns, tiling and designs, in which is provided an overview of geometric designs across various islamic cultures, their compositional styles classified and the constructive composition of representative examples demonstrated. Students assignments mirror these exercises and include simple compositional analyses and developing an islamic design of their own.", "short_name": "ISLAMIC DESIGNS", "co_reqs": [], "instructors": [{"username": "ramesh", "first_name": "Ramesh", "last_name": "Krishnamurti", "tags": [], "hours_per_week": 0, "id": 562, "semesters_taught": [{"semester": 1, "year": 2020}], "photo_url": null}], "anti_reqs": [], "prereqs": {"text": "", "raw_pre_req": "", "req_obj": null}, "is_req_repeatable": false, "topic": null, "name": "Stars, Kites and Darts: A Primer on Islamic Geometric Designs", "base_name": "Stars, Kites and Darts: A Primer on Islamic Geometric Designs", "skills": [], "success": true, "attributes": []}