{"code": "99-152", "offered_in_campuses": [1, 2], "offerings": [{"semesters": [{"semester": 2, "year": 2019}], "sub_semesters": [], "campus_id": 2}], "max_units": 2.0, "is_topic": false, "is_repeatable": false, "admin_context": {"counts_for": [], "suggested_by_advisor": null}, "custom_fields": {"key_topics": null, "prerequisite_knowledge": null, "assessment_structure": null, "goals": null, "relevance": null, "learning_resources": null, "extra_time_commitment": null}, "equiv": [], "student_sets": [{"id": 896, "name": "undergraduate"}], "min_units": 2.0, "offering_tags": [{"sem": 1, "type": "INFO", "name": "specific_sem"}, {"sem": 2, "type": "INFO", "name": "specific_sem"}], "grade_option": {"is_audit": false, "name": "Pass/Fail", "short_name": "P", "never_graded": false, "is_pass_fail": true, "id": 4}, "units": 2.0, "website": null, "long_desc": "THE SPRING 2019 THRIVECMU COURSE IS INTENDED FOR FIRSTYEAR STUDENTS ONLY.  ThriveCMU is a course that promotes personal development through selfassessment, peerdiscussion and reflection. Each week, a different theme will be brought to life with the help of a facultystaff expert who will help lead discussions, offer new insights and identify strategies for real world application of the course material. Themes addressed in this mini will include balancing academic and campus involvement, relationships, holistic health, stress and passion. Ultimately, the goal of this course is to ease the transition to CMU and build a strong foundation for students to have a thriving undergraduate experience. The course will be structured in a friendly, guided forum the promotes discussion and offers personal and collective exploration of the self, academic and cocurricular opportunities and challenges students may encounter over their time at CMU. If you have questions related to this course please contact Aaron George at atgeorgeandrew.cmu.edu.", "short_name": "THRIVE@CMU", "co_reqs": [], "instructors": [{"username": "drehal", "first_name": "Dalia", "last_name": "Rehal", "tags": [], "hours_per_week": 0, "id": 3930, "semesters_taught": [{"semester": 2, "year": 2019}], "photo_url": null}], "anti_reqs": [], "prereqs": {"text": "", "raw_pre_req": "", "req_obj": null}, "is_req_repeatable": false, "topic": null, "name": "Thrive@CMU", "base_name": "Thrive@CMU", "skills": [], "success": true, "attributes": []}